TextFinder/TextFinder.py
TextFinder/__init__.py
TextFinder-0.0.1.dist-info/LICENSE.txt
TextFinder-0.0.1.dist-info/METADATA
TextFinder-0.0.1.dist-info/WHEEL
TextFinder-0.0.1.dist-info/top_level.txt
TextFinder-0.0.1.dist-info/RECORD
